pbinance/__init__.py
pbinance/client.py
pbinance/proxy_host.py
pbinance/cm_future/__init__.py
pbinance/cm_future/cm_account_trade.py
pbinance/cm_future/cm_market.py
pbinance/cm_future/cm_portfolio_margin.py
pbinance/european_options/__init__.py
pbinance/european_options/eo_account_trade.py
pbinance/european_options/eo_market.py
pbinance/european_options/eo_market_maker.py
pbinance/margin/__init__.py
pbinance/margin/margin_account_trade.py
pbinance/other/__init__.py
pbinance/other/blvt.py
pbinance/other/bs_wap.py
pbinance/other/c2c.py
pbinance/other/convert.py
pbinance/other/crypto_loans.py
pbinance/other/fiat.py
pbinance/other/futures.py
pbinance/other/futures_algo.py
pbinance/other/giftcard.py
pbinance/other/mining.py
pbinance/other/nft.py
pbinance/other/pay.py
pbinance/other/rebate.py
pbinance/other/savings.py
pbinance/other/staking.py
pbinance/other/sub_account.py
pbinance/other/vip_loans.py
pbinance/spot/__init__.py
pbinance/spot/spot_account_trade.py
pbinance/spot/spot_market.py
pbinance/spot/spot_portfolio_margin.py
pbinance/spot/wallet.py
pbinance/um_future/__init__.py
pbinance/um_future/um_account_trade.py
pbinance/um_future/um_market.py
pbinance/um_future/um_portfolio_margin.py
pbinance-1.0.11.dist-info/METADATA
pbinance-1.0.11.dist-info/WHEEL
pbinance-1.0.11.dist-info/top_level.txt
pbinance-1.0.11.dist-info/RECORD
