Metadata-Version: 2.1
Name: pbinance
Version: 1.0.11
Summary: Python Binance API interface
Home-page: https://github.com/pyted/pbinance
Author: pyted
Author-email: pyted@outlook.com
License: MIT
Classifier: License :: OSI Approved :: MIT License
Classifier: Programming Language :: Python
Classifier: Programming Language :: Python :: 3
Classifier: Programming Language :: Python :: 3.6
Classifier: Programming Language :: Python :: Implementation :: CPython
Classifier: Programming Language :: Python :: Implementation :: PyPy
Requires-Python: >=3.6.0
Requires-Dist: requests
Requires-Dist: paux
